cocobase-0.3.2.dist-info/licenses/LICENSE
cocobase_client/__init__.py
cocobase_client/auth.py
cocobase_client/client.py
cocobase_client/config.py
cocobase_client/exceptions.py
cocobase_client/file_manager.py
cocobase_client/query.py
cocobase_client/record.py
cocobase_client/types.py
tests/app.py
tests/test_client.py
cocobase-0.3.2.dist-info/METADATA
cocobase-0.3.2.dist-info/WHEEL
cocobase-0.3.2.dist-info/top_level.txt
cocobase-0.3.2.dist-info/RECORD
