Metadata-Version: 2.4
Name: cocobase
Version: 0.3.2
Summary: The python client for the Cocobase BAAS
Author-email: Patrick Chidera <lordyacey@gmail.com>
License: MIT
Requires-Python: >=3.7
License-File: LICENSE
Requires-Dist: requests
Dynamic: license-file
